xchainpy2_crypto/__init__.py
xchainpy2_crypto/keystore.py
xchainpy2_crypto/utils.py
xchainpy2_crypto/tests/__init__.py
xchainpy2_crypto/tests/test_address.py
xchainpy2_crypto/tests/test_keystore.py
xchainpy2_crypto/tests/test_mnemonic.py
xchainpy2_crypto-0.0.8.dist-info/LICENSE
xchainpy2_crypto-0.0.8.dist-info/METADATA
xchainpy2_crypto-0.0.8.dist-info/WHEEL
xchainpy2_crypto-0.0.8.dist-info/top_level.txt
xchainpy2_crypto-0.0.8.dist-info/RECORD
